pygerm.cpython-311-darwin.so
pygerm-0.0.4.dist-info/LICENSE
pygerm-0.0.4.dist-info/METADATA
pygerm-0.0.4.dist-info/WHEEL
pygerm-0.0.4.dist-info/top_level.txt
pygerm-0.0.4.dist-info/RECORD
