Metadata-Version: 2.1
Name: pygerm
Version: 0.0.4
Summary: A powerful, component based, 2D Python game engine
Author: Jeremy Liu
Author-email: jeremylliu@umich.edu
Requires-Python: >=3.7
License-File: LICENSE
Provides-Extra: test
Requires-Dist: pytest >=6.0 ; extra == 'test'
